pysimulators-1.2.3.dist-info/RECORD
pysimulators-1.2.3.dist-info/LICENSE
pysimulators-1.2.3.dist-info/WHEEL
pysimulators-1.2.3.dist-info/top_level.txt
pysimulators-1.2.3.dist-info/METADATA
pysimulators-1.2.3.dist-info/LICENCE_FR
pysimulators/acquisitions.py
pysimulators/warnings.py
pysimulators/beams.py
pysimulators/__init__.py
pysimulators/quantities.py
pysimulators/datautils.py
pysimulators/mpiutils.py
pysimulators/instruments.py
pysimulators/datatypes.py
pysimulators/geometry.py
pysimulators/sparse.py
pysimulators/operators.py
pysimulators/_flib.cpython-310-darwin.so
pysimulators/wcsutils.py
pysimulators/noises.py
pysimulators/packedtables/samplings.py
pysimulators/packedtables/__init__.py
pysimulators/packedtables/core.py
pysimulators/packedtables/scenes.py
pysimulators/packedtables/layouts.py
pysimulators/.dylibs/libgfortran.5.dylib
pysimulators/.dylibs/libquadmath.0.dylib
pysimulators/.dylibs/libgcc_s.1.dylib
pysimulators/.dylibs/libgomp.1.dylib
pysimulators/interfaces/__init__.py
pysimulators/interfaces/madmap1.py
pysimulators/interfaces/healpy/__init__.py
pysimulators/interfaces/healpy/scenes.py
pysimulators/interfaces/healpy/operators.py
