Metadata-Version: 2.1
Name: pysimulators
Version: 1.2.3
Summary: Tools to build an instrument model.
Author-email: Pierre Chanial <pierre.chanial@gmail.com>
Maintainer-email: Pierre Chanial <pierre.chanial@gmail.com>
License: CeCILL-B FREE SOFTWARE LICENSE AGREEMENT
Project-URL: homepage, https://pchanial.github.io/pysimulators
Project-URL: repository, https://github.com/pchanial/pysimulators
Keywords: scientific computing
Classifier: Programming Language :: Python
Classifier: Programming Language :: Python :: 3.8
Classifier: Programming Language :: Python :: 3.9
Classifier: Programming Language :: Python :: 3.10
Classifier: Programming Language :: Fortran
Classifier: Development Status :: 5 - Production/Stable
Classifier: Intended Audience :: Science/Research
Classifier: Operating System :: OS Independent
Classifier: Topic :: Scientific/Engineering
Classifier: Topic :: Scientific/Engineering :: Astronomy
Classifier: Topic :: Scientific/Engineering :: Atmospheric Science
Classifier: Topic :: Scientific/Engineering :: Information Analysis
Classifier: Topic :: Scientific/Engineering :: Medical Science Apps.
Classifier: Topic :: Scientific/Engineering :: Physics
Requires-Python: >=3.8
Provides-Extra: healpix
Provides-Extra: dev
License-File: LICENCE_FR
License-File: LICENSE
